ANNOUNCEMENT.rst
LICENSE.txt
MANIFEST.in
README.rst
RELEASE_NOTES.rst
requirements.txt
requirements_test.txt
setup.py
pyorcy/__init__.py
pyorcy/cli.py
pyorcy/version.py
pyorcy.egg-info/PKG-INFO
pyorcy.egg-info/SOURCES.txt
pyorcy.egg-info/dependency_links.txt
pyorcy.egg-info/entry_points.txt
pyorcy.egg-info/requires.txt
pyorcy.egg-info/top_level.txt
pyorcy/tests/__init__.py
pyorcy/tests/compute.py
pyorcy/tests/test_simple.py