Metadata-Version: 1.1
Name: pyorcy
Version: 0.1.2
Summary: Mix Python and Cython code in the same module.
Home-page: https://github.com/blosc/bloscpack
Author: Marko Loparic, Francesc Alted
Author-email: marko.loparic@gmail.com, faltet@gmail.com
License: MIT
Keywords: compression,applied information theory
Platform: UNKNOWN
Classifier: Development Status :: 3 - Alpha
Classifier: Environment :: Console
Classifier: License :: OSI Approved :: MIT License
Classifier: Operating System :: Microsoft :: Windows
Classifier: Operating System :: POSIX
Classifier: Programming Language :: Python
Classifier: Topic :: Scientific/Engineering
Classifier: Topic :: Utilities
Classifier: Programming Language :: Python
Classifier: Programming Language :: Python :: 2.6
Classifier: Programming Language :: Python :: 2.7
Classifier: Programming Language :: Python :: 3.4
Classifier: Programming Language :: Python :: 3.5
